vittles/__init__.py
vittles/_version.py
vittles/bivariate_sensitivity_lib.py
vittles/lr_cov_lib.py
vittles/sensitivity_lib.py
vittles/solver_lib.py
vittles/sparse_hessian_lib.py
vittles-0.173.dist-info/AUTHORS.rst
vittles-0.173.dist-info/LICENSE
vittles-0.173.dist-info/METADATA
vittles-0.173.dist-info/WHEEL
vittles-0.173.dist-info/entry_points.txt
vittles-0.173.dist-info/top_level.txt
vittles-0.173.dist-info/RECORD
