Metadata-Version: 2.1
Name: vittles
Version: 0.173
Summary: Python package to estimate sensitivity of optima to hyperparameters.
Home-page: https://github.com/rgiordan/vittles
Author: Ryan Giordano
Author-email: rgiordan@gmail.com
License: UNKNOWN
Platform: UNKNOWN
Classifier: Programming Language :: Python :: 3
Classifier: Natural Language :: English
Classifier: License :: OSI Approved :: Apache Software License
Classifier: Intended Audience :: Science/Research
Classifier: Intended Audience :: Developers
Classifier: Development Status :: 2 - Pre-Alpha
Classifier: Topic :: Scientific/Engineering :: Mathematics
Requires-Dist: autograd (>=1.3)
Requires-Dist: numpy
Requires-Dist: paragami (>=0.42)
Requires-Dist: pytest
Requires-Dist: scipy
